ext_argparse/__init__.py
ext_argparse/argproc.py
ext_argparse/param_enum.py
ext_argparse/parameter.py
ext_argparse-0.1.2.dist-info/LICENSE
ext_argparse-0.1.2.dist-info/METADATA
ext_argparse-0.1.2.dist-info/WHEEL
ext_argparse-0.1.2.dist-info/top_level.txt
ext_argparse-0.1.2.dist-info/RECORD
